breizhcrops/__init__.py
breizhcrops/utils.py
breizhcrops/datasets/__init__.py
breizhcrops/datasets/breizhcrops.py
breizhcrops/datasets/urls.py
breizhcrops/models/InceptionTime.py
breizhcrops/models/LongShortTermMemory.py
breizhcrops/models/MSResNet.py
breizhcrops/models/OmniScaleCNN.py
breizhcrops/models/PETransformerModel.py
breizhcrops/models/StarRNN.py
breizhcrops/models/TempCNN.py
breizhcrops/models/TransformerModel.py
breizhcrops/models/__init__.py
breizhcrops/models/pretrained.py
breizhcrops-0.0.4.1.dist-info/LICENSE
breizhcrops-0.0.4.1.dist-info/METADATA
breizhcrops-0.0.4.1.dist-info/WHEEL
breizhcrops-0.0.4.1.dist-info/top_level.txt
breizhcrops-0.0.4.1.dist-info/RECORD
