Metadata-Version: 2.1
Name: breizhcrops
Version: 0.0.4.1
Summary: A Satellite Time Series Dataset for Crop Type Identification
Home-page: http://github.com/dl4sits/breizhcrops
Author: Marc Rußwurm, Charlotte Pelletier, Max Zollner
Author-email: marc.russwurm@tum.de
License: MIT
Platform: UNKNOWN
Requires-Dist: geopandas (>=0.5.0)
Requires-Dist: numpy
Requires-Dist: pandas (>=0.24.2)
Requires-Dist: geojson (>=2.4.1)
Requires-Dist: jupyter (>=1.0.0)
Requires-Dist: matplotlib (>=3.1.0)
Requires-Dist: seaborn (>=0.9.0)
Requires-Dist: torch (>=1.6.0)
Requires-Dist: tqdm (>=4.32.2)
Requires-Dist: scikit-learn
Requires-Dist: h5py
Requires-Dist: requests
Requires-Dist: pytest
